xwr/__init__.py
xwr/config.py
xwr/py.typed
xwr/system.py
xwr/capture/__init__.py
xwr/capture/api.py
xwr/capture/defines.py
xwr/capture/types.py
xwr/nn/__init__.py
xwr/nn/backend.py
xwr/nn/representations.py
xwr/nn/utils.py
xwr/radar/__init__.py
xwr/radar/api.py
xwr/radar/base.py
xwr/radar/defines.py
xwr/radar/raw.py
xwr/rsp/__init__.py
xwr/rsp/generic.py
xwr/rsp/jax/__init__.py
xwr/rsp/jax/aoa.py
xwr/rsp/jax/rsp.py
xwr/rsp/jax/spectrum.py
xwr/rsp/numpy/__init__.py
xwr/rsp/numpy/rsp.py
xwr/rsp/torch/__init__.py
xwr/rsp/torch/rsp.py
xwr-0.3.5.dist-info/METADATA
xwr-0.3.5.dist-info/WHEEL
xwr-0.3.5.dist-info/licenses/LICENSE
xwr-0.3.5.dist-info/RECORD
