Metadata-Version: 2.4
Name: xwr
Version: 0.3.5
Summary: Linux-Compatible Real-Time Raw Data Capture for TI mmWave Radars.
Project-URL: Homepage, https://github.com/RadarML/xwr
Project-URL: Documentation, https://radarml.github.io/xwr
Project-URL: Issues, https://github.com/RadarML/xwr/issues
Author-email: Tianshu Huang <tianshu2@andrew.cmu.edu>
License-Expression: MIT
License-File: LICENSE
Classifier: Operating System :: POSIX :: Linux
Classifier: Programming Language :: Python :: 3.10
Classifier: Programming Language :: Python :: 3.11
Classifier: Programming Language :: Python :: 3.12
Classifier: Programming Language :: Python :: 3.13
Classifier: Typing :: Typed
Requires-Python: >=3.10
Requires-Dist: beartype>=0.20
Requires-Dist: jaxtyping>=0.3.2
Requires-Dist: numpy>=1.19
Requires-Dist: pyfftw>=0.15.0
Requires-Dist: pyserial>=3.5
Requires-Dist: types-pyserial>=3.5
Provides-Extra: dev
Requires-Dist: coverage; extra == 'dev'
Requires-Dist: pre-commit>=4.0.0; extra == 'dev'
Requires-Dist: pyright>=1.0.0; extra == 'dev'
Requires-Dist: pytest-cov; extra == 'dev'
Requires-Dist: pytest>=8.0.0; extra == 'dev'
Requires-Dist: ruff>=0.11.0; extra == 'dev'
Provides-Extra: docs
Requires-Dist: abstract-dataloader>=0.3.5; extra == 'docs'
Requires-Dist: griffe==1.8.0; extra == 'docs'
Requires-Dist: mkdocs-material==9.6.*; extra == 'docs'
Requires-Dist: mkdocs==1.6.*; extra == 'docs'
Requires-Dist: mkdocstrings-python-xref==1.16.3; extra == 'docs'
Requires-Dist: mkdocstrings-python==1.16.6; extra == 'docs'
Requires-Dist: ruff>=0.11.0; extra == 'docs'
Provides-Extra: jax
Requires-Dist: jax>=0.4.0; extra == 'jax'
Provides-Extra: nn
Requires-Dist: torch>=2.0; extra == 'nn'
Requires-Dist: torchvision>=0.15.0; extra == 'nn'
Provides-Extra: torch
Requires-Dist: torch>=2.0; extra == 'torch'
